CHANGES
LICENSE
MANIFEST.in
README.rst
setup.cfg
setup.py
Natume.egg-info/PKG-INFO
Natume.egg-info/SOURCES.txt
Natume.egg-info/dependency_links.txt
Natume.egg-info/top_level.txt
examples/xiami.smoke
natume/__init__.py
natume/__main__.py
natume/client.py
natume/compat.py
natume/connection.py
natume/parser.py
natume/testcase.py
natume/util.py
test/__init__.py
test/clienttest.py
test/testcasetest.py
test/utiltest.py