Metadata-Version: 1.1
Name: Natume
Version: 0.1.0
Summary: HTTP DSL Test Tool
Home-page: https://github.com/thomashuang/natume
Author: Thomas Huang
Author-email: lyanghwy@gmail.com
License: GPL 2
Keywords: http,test
Platform: UNKNOWN
Classifier: Development Status :: 5 - Production/Stable
Classifier: Environment :: Web Environment
Classifier: Intended Audience :: Developers
Classifier: Programming Language :: Python
Classifier: Programming Language :: Python :: 3
Classifier: Programming Language :: Python :: Implementation :: CPython
Classifier: Programming Language :: Python :: Implementation :: PyPy
Classifier: Topic :: Internet :: WWW/HTTP :: Dynamic Content
